{"dataResult":{"createdDate":"2024-09-30T06:16:13Z","dataSourceID":"A3CC515E-3088-4064-A668-EB858EBD91E5","dataURL":"file:\/\/\/Users\/sebastianstoelen\/Workspace\/100daysSwiftUI\/Github%20files\/SwiftUI\/project4-files\/BetterRest.csv"},"modifiedDate":"2024-09-30T06:17:09Z","experimentIDs":["546EDEB1-D2EB-4E35-9482-8E037F2B8528"],"activityEntities":["dataSourceTrainingStarted",[{"id":"08DF8F6E-AFAF-41F5-B2AE-609017D3C048","title":"Used By","subtitle":"BetterRest 1","createdDate":"2024-09-30T06:17:09Z","event":"dataSourceTrainingStarted"}],"dataSourceMetrics",[{"createdDate":"2024-09-30T06:17:09Z","subtitle":"10.000 Items","event":"dataSourceMetrics","title":"Data Summary","id":"51979794-2249-4096-9C62-6503AAE15D46"}]],"pathType":0,"dataURL":"file:\/\/\/Users\/sebastianstoelen\/Workspace\/100daysSwiftUI\/Github%20files\/SwiftUI\/project4-files\/BetterRest.csv","preferredFilename":"BetterRest.csv","id":"A3CC515E-3088-4064-A668-EB858EBD91E5","createdDate":"2024-09-30T06:16:13Z","version":"1.0","title":"BetterRest.csv","dataPathRelativeToProjectURL":"..\/..\/Github%20files\/SwiftUI\/project4-files\/BetterRest.csv\/"}